tometo_tomato/__init__.py
tometo_tomato/tometo_tomato.py
tometo_tomato-0.0.1.dist-info/licenses/LICENSE
tometo_tomato-0.0.1.dist-info/METADATA
tometo_tomato-0.0.1.dist-info/WHEEL
tometo_tomato-0.0.1.dist-info/entry_points.txt
tometo_tomato-0.0.1.dist-info/top_level.txt
tometo_tomato-0.0.1.dist-info/RECORD
