Metadata-Version: 2.4
Name: tometo_tomato
Version: 0.0.1
Summary: A fuzzy join utility using DuckDB
Author-email: Andrea Borruso <andrea.borruso@gmail.com>
License: MIT License
Project-URL: Homepage, https://github.com/aborruso/tometo_tomato
Project-URL: Bug Tracker, https://github.com/aborruso/tometo_tomato/issues
Keywords: duckdb,fuzzy-join,etl,data-processing
Classifier: Programming Language :: Python :: 3
Classifier: License :: OSI Approved :: MIT License
Classifier: Operating System :: OS Independent
Requires-Python: >=3.8
License-File: LICENSE
Requires-Dist: duckdb
Requires-Dist: rapidfuzz
Requires-Dist: numpy
Dynamic: license-file
